summary.py
csv_citation_counter-0.1.0.dist-info/METADATA
csv_citation_counter-0.1.0.dist-info/WHEEL
csv_citation_counter-0.1.0.dist-info/entry_points.txt
csv_citation_counter-0.1.0.dist-info/top_level.txt
csv_citation_counter-0.1.0.dist-info/RECORD
