Metadata-Version: 2.4
Name: csv-citation-counter
Version: 0.1.0
Summary: Summarize CSV publication and citation data by column.
Author: Tiger Deng
License-Expression: MIT
Classifier: Programming Language :: Python :: 3
Classifier: Operating System :: OS Independent
Requires-Python: >=3.8
